tnk/__init__.py
tnk/build_autoencoder.py
tnk-0.0.1.dist-info/LICENSE
tnk-0.0.1.dist-info/METADATA
tnk-0.0.1.dist-info/WHEEL
tnk-0.0.1.dist-info/top_level.txt
tnk-0.0.1.dist-info/RECORD
